moear-1.0.0a2.dist-info/METADATA
moear-1.0.0a2.dist-info/RECORD
moear-1.0.0a2.dist-info/WHEEL
moear-1.0.0a2.dist-info/top_level.txt
server/__init__.py
server/manage.py
server/core/__init__.py
server/core/adapters.py
server/core/admin.py
server/core/apps.py
server/core/models.py
server/core/serializers.py
server/core/tasks.py
server/core/tests.py
server/core/views.py
server/core/fixtures/Option.json
server/core/fixtures/Site.json
server/core/fixtures/User.json
server/core/management/__init__.py
server/core/management/commands/__init__.py
server/core/management/commands/create_superuser.py
server/core/migrations/0001_initial.py
server/core/migrations/__init__.py
server/deliver/__init__.py
server/deliver/admin.py
server/deliver/apps.py
server/deliver/models.py
server/deliver/serializers.py
server/deliver/tasks.py
server/deliver/tests.py
server/deliver/views.py
server/deliver/migrations/0001_initial.py
server/deliver/migrations/__init__.py
server/pages/__init__.py
server/pages/apps.py
server/pages/tests.py
server/pages/urls.py
server/pages/views.py
server/pages/migrations/__init__.py
server/pages/static/css/app.css
server/pages/static/js/app.js
server/posts/__init__.py
server/posts/admin.py
server/posts/apps.py
server/posts/models.py
server/posts/serializers.py
server/posts/tasks.py
server/posts/tests.py
server/posts/utils.py
server/posts/views.py
server/posts/fixtures/Post.json
server/posts/fixtures/PostMeta.json
server/posts/migrations/0001_initial.py
server/posts/migrations/__init__.py
server/restapi/__init__.py
server/restapi/urls.py
server/server/__init__.py
server/server/celery.py
server/server/settings.py
server/server/urls.py
server/server/wsgi.py
server/server/options/__init__.py
server/spiders/__init__.py
server/spiders/admin.py
server/spiders/apps.py
server/spiders/models.py
server/spiders/serializers.py
server/spiders/tasks.py
server/spiders/tests.py
server/spiders/views.py
server/spiders/fixtures/Spider.json
server/spiders/fixtures/SpiderMeta.json
server/spiders/management/__init__.py
