Metadata-Version: 2.1
Name: moear
Version: 1.0.0a2
Summary: 用来实现对网络文章的爬取、mobi打包、并推送到Kindle设备上
Home-page: https://github.com/littlemo/moear
Author: moear developers
Author-email: moore@moorehy.com
Maintainer: littlemo
Maintainer-email: moore@moorehy.com
License: GPLv3
Project-URL: Source, https://github.com/littlemo/moear
Project-URL: Documentation, http://moear.rtfd.io/
Project-URL: Tracker, https://github.com/littlemo/moear/issues
Keywords: moear post rss kindle mobi
Platform: UNKNOWN
Classifier: Development Status :: 3 - Alpha
Classifier: Environment :: Console
Classifier: Environment :: Web Environment
Classifier: Framework :: Django
Classifier: Framework :: Django :: 2.0
Classifier: Intended Audience :: Customer Service
Classifier: License :: OSI Approved :: GNU General Public License v3 (GPLv3)
Classifier: Natural Language :: Chinese (Simplified)
Classifier: Operating System :: POSIX :: Linux
Classifier: Programming Language :: Python :: 3
Classifier: Programming Language :: Python :: 3 :: Only
Classifier: Programming Language :: Python :: 3.5
Classifier: Topic :: Communications :: Email
Classifier: Topic :: Documentation :: Sphinx
Classifier: Topic :: Internet
Classifier: Topic :: Software Development :: Version Control :: Git
Classifier: Topic :: Software Development :: Libraries :: Python Modules
Classifier: Topic :: System :: Networking
Classifier: Topic :: Internet :: WWW/HTTP
Classifier: Topic :: Internet :: WWW/HTTP :: Dynamic Content
Classifier: Topic :: Terminals
Classifier: Topic :: Utilities
Requires-Python: >=3
Requires-Dist: celery (~=4.1.0)
Requires-Dist: Django (~=2.0.2)
Requires-Dist: django-allauth (~=0.35.0)
Requires-Dist: django-celery-beat (~=1.1.1)
Requires-Dist: django-filter (~=1.1.0)
Requires-Dist: django-invitations (~=1.9.2)
Requires-Dist: djangorestframework (~=3.7.7)
Requires-Dist: gunicorn (~=19.7.1)
Requires-Dist: Markdown (~=2.6.11)
Requires-Dist: moear-api-common (~=1.0.2)
Requires-Dist: moear-package-mobi (~=1.0.0)
Requires-Dist: moear-spider-zhihudaily (~=1.0.0)
Requires-Dist: mysqlclient (~=1.3.12)
Requires-Dist: redis (~=2.10.6)
Requires-Dist: stevedore (~=1.28.0)
